pytmle/__init__.py
pytmle/bootstrap.py
pytmle/estimates.py
pytmle/evalues_benchmark.py
pytmle/g_computation.py
pytmle/get_influence_curve.py
pytmle/get_initial_estimates.py
pytmle/initial_estimates_default_models.py
pytmle/plotting.py
pytmle/predict_ate.py
pytmle/pycox_wrapper.py
pytmle/pytmle.py
pytmle/tmle_update.py
pytmle-0.4.1.dist-info/licenses/LICENSE
pytmle-0.4.1.dist-info/METADATA
pytmle-0.4.1.dist-info/WHEEL
pytmle-0.4.1.dist-info/top_level.txt
pytmle-0.4.1.dist-info/RECORD
