Metadata-Version: 2.4
Name: pytmle
Version: 0.4.1
Summary: A Flexible Python Implementation of Targeted Estimation for Survival and Competing Risks Analysis
License: Apache-2.0
Requires-Python: >=3.9
License-File: LICENSE
Requires-Dist: matplotlib>=3.5.0
Requires-Dist: mlflow>=3.1.0
Requires-Dist: numpy>=1.22.3
Requires-Dist: pandas>=1.3.4
Requires-Dist: pandoc>=2.4
Requires-Dist: pycox
Requires-Dist: scikit-learn>=1.2.2
Requires-Dist: scikit-survival>=0.21.0
Requires-Dist: seaborn>=0.11
Requires-Dist: tqdm>=4.67.1
Provides-Extra: dev
Requires-Dist: ipykernel>=6.29.5; extra == "dev"
Requires-Dist: pytest>=8.3.5; extra == "dev"
Requires-Dist: torch>=2.6.0; extra == "dev"
Dynamic: license-file
